{
  "cloudCover": {
    "excellent": { "min": 4, "max": 5 },
    "good": { "min": 3, "max": 3 },
    "dubious": { "min": 2, "max": 2 },
    "poor": { "min": 1, "max": 1 }
  },
  "transparency": {
    "excellent": { "min": 4, "max": 5 },
    "good": { "min": 3, "max": 3 },
    "dubious": { "min": 2, "max": 2 },
    "poor": { "min": 1, "max": 1 }
  },
  "seeing": {
    "excellent": { "min": 4, "max": 5 },
    "good": { "min": 3, "max": 3 },
    "dubious": { "min": 2, "max": 2 },
    "poor": { "min": 1, "max": 1 }
  },
  "smoke": {
    "excellent": { "min": 4, "max": 5 },
    "good": { "min": 3, "max": 3 },
    "dubious": { "min": 2, "max": 2 },
    "poor": { "min": 1, "max": 1 }
  },
  "wind": {
    "excellent": { "min": 4, "max": 5 },
    "good": { "min": 3, "max": 3 },
    "dubious": { "min": 2, "max": 2 },
    "poor": { "min": 1, "max": 1 }
  },
  "heuristic": "weighted"
}